[
	{
		"name": "gocr_mono",
		"path": "gocr_wasm.so",
		"port": 10000,
		"expected-execution-us": 5000,
		"relative-deadline-us": 36000,
		"http-req-size": 5335057,
		"http-resp-size": 5335057,
		"http-resp-content-type": "text/plain"
	},
	{
		"name": "gocr_urw_gothic",
		"path": "gocr_wasm.so",
		"port": 10001,
		"expected-execution-us": 5000,
		"relative-deadline-us": 36000,
		"http-req-size": 5335057,
		"http-resp-size": 5335057,
		"http-resp-content-type": "text/plain"
	},
	{
		"name": "gocr_lobster_2",
		"path": "gocr_wasm.so",
		"port": 10002,
		"expected-execution-us": 5000,
		"relative-deadline-us": 36000,
		"http-req-size": 5335057,
		"http-resp-size": 5335057,
		"http-resp-content-type": "text/plain"
	}
]